rp23005uno/__init__.py
rp23005uno/lineales.py
rp23005uno/no_lineales.py
rp23005uno-1.0.2.dist-info/licenses/LICENSE
rp23005uno-1.0.2.dist-info/METADATA
rp23005uno-1.0.2.dist-info/WHEEL
rp23005uno-1.0.2.dist-info/top_level.txt
rp23005uno-1.0.2.dist-info/RECORD
