Metadata-Version: 2.4
Name: RP23005UNO
Version: 1.0.2
Summary: Librería para resolver sistemas de ecuaciones
Author-email: Jennifer Pleitez <rp23005@ues.edu.sv>
License: MIT
Project-URL: Repository, https://github.com/rp23005/RP23005UNO.git
Keywords: ecuaciones,álgebra lineal,bisección,gauss,jacobi
Classifier: Programming Language :: Python :: 3
Classifier: License :: OSI Approved :: MIT License
Classifier: Operating System :: OS Independent
Classifier: Intended Audience :: Education
Classifier: Topic :: Scientific/Engineering :: Mathematics
Requires-Python: >=3.10
License-File: LICENSE
Requires-Dist: numpy>=1.24
Dynamic: license-file
